{
  "generated_at": "2026-03-20T17:27:47.486546",
  "input_csv": "data/processed/F_form4_features.csv",
  "params": {
    "horizon_days": 30,
    "benchmark_ticker": "SPY",
    "abnormal_threshold": 0.05,
    "confidence_sources_required": 2,
    "earnings_proximity_days": 30,
    "earnings_csv": "data/external/earnings/earnings_announcements.csv",
    "enforcement_csv": "data/external/sec/sec_enforcement.csv",
    "enforcement_lookahead_days": 365
  },
  "rows": 1345,
  "coverage": {
    "forward_return_rows": 1345,
    "forward_return_pct": 100.0,
    "benchmark_return_rows": 1345,
    "benchmark_return_pct": 100.0
  },
  "labels": {
    "opportunistic_rows": 22,
    "opportunistic_pct": 1.64,
    "routine_rows": 15,
    "routine_pct": 1.12,
    "uncertain_rows": 1308,
    "uncertain_pct": 97.25
  },
  "signals": {
    "price_signal_rows": 450,
    "earnings_signal_rows": 1057,
    "enforcement_signal_rows": 0,
    "label_source_count_distribution": {
      "0": 231,
      "1": 721,
      "2": 393
    }
  },
  "recommendations": [
    "No enforcement confirmations found; provide SEC enforcement CSV for higher-confidence labels."
  ]
}